bcutils/__init__.py
bcutils/bc_utils.py
bcutils/config.py
bcutils/migrate.py
bcutils/tests/__init__.py
bcutils/tests/test_downloader.py
bcutils/tests/test_utils.py
bc_utils-0.1.7.dist-info/LICENSE
bc_utils-0.1.7.dist-info/METADATA
bc_utils-0.1.7.dist-info/WHEEL
bc_utils-0.1.7.dist-info/RECORD
