Metadata-Version: 2.1
Name: bc-utils
Version: 0.1.7
Summary: Python utility automation scripts for Barchart.com
Home-page: https://github.com/bug-or-feature/bc-utils
License: BSD-3-Clause
Keywords: trading
Author: Andy Geach
Author-email: andy@bugorfeature.net
Requires-Python: >=3.8.1,<4.0
Classifier: Development Status :: 3 - Alpha
Classifier: Environment :: Console
Classifier: Intended Audience :: Developers
Classifier: Intended Audience :: Science/Research
Classifier: License :: OSI Approved :: BSD License
Classifier: Operating System :: OS Independent
Classifier: Programming Language :: Cython
Classifier: Programming Language :: Python
Classifier: Programming Language :: Python :: 3
Classifier: Programming Language :: Python :: 3.9
Classifier: Programming Language :: Python :: 3.10
Classifier: Programming Language :: Python :: 3.11
Classifier: Programming Language :: Python :: 3.8
Classifier: Topic :: Scientific/Engineering
Classifier: Topic :: Software Development :: Libraries
Requires-Dist: beautifulsoup4 (>=4,<5)
Requires-Dist: numpy (<2)
Requires-Dist: pandas (<3)
Requires-Dist: pyyaml (>=6.0.1,<7.0.0)
Requires-Dist: requests (>=2,<3)
Project-URL: Issues, https://github.com/bug-or-feature/bc-utils/issues
Project-URL: Repository, https://github.com/bug-or-feature/bc-utils
